bfgbidding/__init__.py
bfgbidding/_version.py
bfgbidding/acol_advancers_bid.py
bfgbidding/acol_advancers_later_bid.py
bfgbidding/acol_advancers_rebid.py
bfgbidding/acol_bidding.py
bfgbidding/acol_openers_bid.py
bfgbidding/acol_openers_later_bid.py
bfgbidding/acol_openers_rebid.py
bfgbidding/acol_openers_third_bid.py
bfgbidding/acol_overcallers_bid.py
bfgbidding/acol_overcallers_rebid.py
bfgbidding/acol_overcallers_third_bid.py
bfgbidding/acol_responders_bid.py
bfgbidding/acol_responders_later_bid.py
bfgbidding/acol_responders_rebid.py
bfgbidding/bidding.py
bfgbidding/blackwood.py
bfgbidding/comment_data/comment_xref.json
bfgbidding/comment_data/comment_xref.zip
bfgbidding/comment_data/comments..zip
bfgbidding/comment_data/comments.json
bfgbidding/comment_data/strategies.json
bfgbidding/comment_data/strategy_xref.json
bfgbidding/comment_xref.py
bfgbidding/comments.py
bfgbidding/constants.py
bfgbidding/hand.py
bfgbidding/logger.py
bfgbidding/player.py
bfgbidding/strategy_xref.py
bfgbidding/tracer.py
bfgbidding/utils.py
bfgbidding-0.1.4.dist-info/WHEEL
bfgbidding-0.1.4.dist-info/METADATA
bfgbidding-0.1.4.dist-info/RECORD
