Metadata-Version: 2.3
Name: bfgbidding
Version: 0.1.4
Summary: Bidding module for BfG
Author: Jeff
Author-email: Jeff <jeffwatkins2000@gmail.com>
Requires-Dist: appdirs>=1.4.4
Requires-Dist: bfgdealer>=0.0.21
Requires-Dist: bridgeobjects>=0.1.30
Requires-Dist: dotenv>=0.9.9
Requires-Dist: icecream>=2.1.8
Requires-Dist: structlog>=25.5.0
Requires-Dist: termcolor>=3.1.0
Requires-Python: ==3.10.17
